{
  "total_live_events": 204,
  "tag_format": {
    "total_with_tags": 204,
    "parse_failures": 0,
    "failure_pct": 0
  },
  "field_completeness": {
    "title": 100,
    "age_min": 54.9,
    "age_best_from": 100,
    "age_best_to": 100,
    "age_label": 100,
    "next_start_at": 96.6,
    "price_max": 100,
    "is_free": 58.8,
    "category_l1": 97.5,
    "format": 96.1,
    "motivation": 92.6,
    "country_county": 84.8,
    "subway": 73.5,
    "rating_count_ge5": 82.8,
    "rating_count_ge20": 54.4,
    "lat_lon": 100,
    "tags_nonempty": 100,
    "categories_nonempty": 3.4
  },
  "distributions": {
    "by_county": {
      "New York County": 64,
      "Suffolk County": 30,
      "": 31,
      "Kings County": 42,
      "Bronx County": 14,
      "Queens County": 11,
      "Nassau County": 10,
      "Rockland County": 1,
      "Westchester County": 1
    },
    "by_category_l1": {
      "family": 115,
      "arts": 10,
      "gaming": 1,
      "science": 2,
      "music": 14,
      "outdoors": 7,
      "theater": 8,
      "community": 11,
      "attractions": 4,
      "education": 4,
      "books": 3,
      "nightlife": 1,
      "networking": 1,
      "comedy": 3,
      "sports": 11,
      "food": 2,
      "": 5,
      "wellness": 1,
      "holiday": 1
    },
    "by_format": {
      "['class', 'workshop']": 1,
      "": 8,
      "['class', 'workshop', 'museum-visit']": 1,
      "['exhibition']": 1,
      "['exhibition', 'museum-visit']": 4,
      "['workshop', 'class']": 5,
      "['museum-visit', 'tour', 'kids-playgroup']": 1,
      "['kids-playgroup', 'meetup', 'live-performance']": 1,
      "['museum-visit', 'kids-playgroup']": 1,
      "['class', 'guided-walk']": 1,
      "['live-performance', 'kids-playgroup']": 1,
      "['live-performance', 'theater-show']": 9,
      "['class', 'community-service']": 1,
      "['museum-visit', 'workshop', 'kids-playgroup']": 2,
      "['tour', 'workshop', 'class', 'kids-playgroup']": 1,
      "['museum-visit', 'guided-walk', 'workshop']": 1,
      "['sports-event', 'kids-playgroup', 'workshop', 'competition']": 1,
      "['class', 'workshop', 'kids-playgroup', 'live-performance']": 1,
      "['festival', 'live-performance', 'workshop', 'kids-playgroup']": 1,
      "['workshop', 'community-service']": 1,
      "['party', 'live-performance', 'workshop']": 1,
      "['sports-event', 'workshop', 'meetup', 'training-session', 'guided-walk']": 1,
      "['guided-walk', 'hike', 'community-service']": 1,
      "['workshop', 'kids-playgroup', 'guided-walk']": 2,
      "['workshop', 'kids-playgroup', 'museum-visit']": 1,
      "['museum-visit', 'workshop', 'live-performance']": 1,
      "['guided-walk', 'museum-visit', 'workshop', 'kids-playgroup']": 1,
      "['museum-visit', 'workshop', 'live-performance', 'guided-walk']": 1,
      "['concert', 'live-performance', 'kids-playgroup']": 1,
      "['live-performance', 'workshop']": 2,
      "['festival', 'live-performance', 'workshop']": 1,
      "['fair', 'kids-playgroup']": 2,
      "['concert', 'live-performance']": 11,
      "['theater-show', 'live-performance']": 5,
      "['kids-playgroup', 'workshop', 'museum-visit']": 1,
      "['festival', 'workshop', 'screening', 'meetup']": 1,
      "['festival', 'exhibition', 'guided-walk', 'community-service']": 1,
      "['workshop', 'guided-walk']": 1,
      "['fair', 'workshop', 'community-service']": 1,
      "['workshop', 'kids-playgroup']": 6,
      "['open-day', 'workshop', 'guided-walk']": 1,
      "['festival', 'tour', 'live-performance', 'workshop']": 1,
      "['festival', 'guided-walk', 'workshop']": 1,
      "['kids-playgroup', 'guided-walk', 'community-service']": 1,
      "['kids-playgroup', 'guided-walk', 'museum-visit']": 1,
      "['festival', 'kids-playgroup']": 1,
      "['exhibition', 'open-day']": 1,
      "['guided-walk', 'tour', 'workshop', 'kids-playgroup']": 1,
      "['live-performance', 'workshop', 'kids-playgroup']": 1,
      "['workshop', 'class', 'kids-playgroup']": 3,
      "['workshop', 'class', 'training-session']": 1,
      "['class', 'workshop', 'training-session', 'kids-playgroup']": 1,
      "['festival', 'kids-playgroup', 'community-service']": 1,
      "['workshop', 'live-performance']": 2,
      "['live-performance']": 1,
      "['meetup', 'workshop', 'kids-playgroup', 'community-service']": 1,
      "['live-performance', 'talk', 'meetup', 'kids-playgroup']": 1,
      "['market', 'workshop']": 2,
      "['community-service', 'workshop', 'kids-playgroup']": 1,
      "['class', 'training-session']": 1,
      "['kids-playgroup', 'live-performance']": 2,
      "['exhibition', 'tour', 'workshop']": 1,
      "['fair', 'meetup']": 1,
      "['workshop', 'kids-playgroup', 'class']": 1,
      "['lecture', 'talk']": 1,
      "['party', 'kids-playgroup']": 2,
      "['community-service', 'workshop']": 1,
      "['talk', 'live-performance', 'meetup', 'online-event']": 1,
      "['kids-playgroup', 'live-performance', 'workshop']": 1,
      "['competition', 'class']": 1,
      "['party', 'networking-event']": 2,
      "['party', 'live-performance']": 1,
      "['talk', 'workshop']": 1,
      "['class', 'kids-playgroup']": 2,
      "['live-performance', 'meetup']": 1,
      "['concert', 'kids-playgroup']": 1,
      "['kids-playgroup', 'workshop', 'meetup']": 1,
      "['party', 'club-night']": 1,
      "['live-performance', 'guided-walk', 'meetup']": 1,
      "['competition', 'meetup']": 1,
      "['class', 'open-day', 'kids-playgroup']": 1,
      "['tour', 'workshop']": 1,
      "['class', 'kids-playgroup', 'open-day']": 1,
      "['guided-walk', 'kids-playgroup']": 1,
      "['kids-playgroup', 'workshop', 'guided-walk']": 1,
      "['meetup']": 1,
      "['kids-playgroup', 'camp']": 1,
      "['conference', 'workshop', 'talk', 'networking-event']": 1,
      "['live-performance', 'festival']": 1,
      "['conference', 'lecture', 'talk', 'networking-event']": 1,
      "['kids-playgroup', 'class', 'meetup']": 1,
      "['workshop', 'guided-walk', 'kids-playgroup']": 2,
      "['workshop', 'guided-walk', 'museum-visit']": 1,
      "['community-service']": 1,
      "['tour', 'guided-walk']": 1,
      "['live-performance', 'concert']": 1,
      "['guided-walk', 'hike', 'tour']": 1,
      "['live-performance', 'talk']": 1,
      "['live-performance', 'screening']": 1,
      "['guided-walk', 'tour']": 2,
      "['festival', 'kids-playgroup', 'guided-walk']": 1,
      "['concert', 'live-performance', 'exhibition', 'workshop']": 1,
      "['festival', 'workshop', 'sports-event', 'live-performance']": 1,
      "['workshop', 'talk', 'meetup']": 1,
      "['festival', 'workshop', 'tour']": 1,
      "['workshop', 'kids-playgroup', 'live-performance']": 1,
      "['festival', 'workshop', 'guided-walk']": 2,
      "['workshop', 'museum-visit', 'guided-walk', 'kids-playgroup']": 1,
      "['sports-event', 'kids-playgroup', 'community-service']": 1,
      "['kids-playgroup', 'museum-visit']": 2,
      "['community-service', 'kids-playgroup']": 1,
      "['meetup', 'class']": 1,
      "['museum-visit', 'guided-walk']": 1,
      "['sports-event', 'community-service']": 1,
      "['sports-event', 'tour']": 1,
      "['sports-event', 'guided-walk', 'community-service']": 1,
      "['sports-event', 'competition']": 3,
      "['fair', 'festival', 'workshop', 'kids-playgroup']": 1,
      "['market']": 1,
      "['kids-playgroup', 'screening', 'workshop']": 1,
      "['sports-event', 'guided-walk']": 1,
      "['sports-event', 'competition', 'meetup']": 1,
      "['open-day', 'kids-playgroup']": 1,
      "['sports-event', 'meetup']": 1,
      "['sports-event', 'competition', 'community-service']": 2,
      "['sports-event', 'community-service', 'competition']": 1,
      "['festival', 'class', 'workshop', 'sports-event']": 1,
      "['market', 'workshop', 'meetup']": 1,
      "['live-performance', 'talk', 'meetup']": 1,
      "['workshop']": 2,
      "[]": 1,
      "['museum-visit', 'exhibition']": 1,
      "['workshop', 'museum-visit', 'kids-playgroup', 'live-performance']": 1,
      "['kids-playgroup', 'exhibition']": 1,
      "['festival', 'guided-walk']": 1,
      "['fair', 'market', 'exhibition']": 1,
      "storytelling": 2,
      "outdoor-activity": 4,
      "museum-visit": 1
    },
    "by_motivation": {
      "['learn', 'create', 'bond']": 9,
      "": 15,
      "['learn', 'create', 'explore']": 1,
      "['learn', 'play', 'bond']": 21,
      "['learn', 'explore', 'be-inspired']": 1,
      "['play', 'bond', 'learn']": 4,
      "['learn', 'create', 'relax']": 1,
      "['bond', 'play', 'celebrate']": 5,
      "['explore', 'learn', 'bond']": 3,
      "['learn', 'bond', 'play']": 12,
      "['be-entertained', 'bond', 'learn']": 2,
      "['be-entertained', 'bond', 'play']": 2,
      "['bond', 'socialize', 'learn']": 1,
      "['play', 'improve-health', 'bond']": 1,
      "['play', 'bond', 'be-entertained']": 2,
      "['play', 'bond', 'create']": 2,
      "['learn', 'bond', 'support-community']": 1,
      "['bond', 'play', 'be-entertained']": 5,
      "['play', 'bond', 'celebrate']": 1,
      "['learn', 'play', 'improve-health']": 1,
      "['explore', 'improve-health', 'bond']": 1,
      "['play', 'create', 'learn']": 2,
      "['be-entertained', 'be-inspired', 'explore']": 2,
      "['learn', 'bond', 'create']": 1,
      "['bond', 'play', 'learn']": 12,
      "['learn', 'bond', 'explore']": 1,
      "['play', 'learn', 'be-entertained']": 1,
      "['be-entertained', 'bond']": 3,
      "['play', 'bond', 'explore']": 2,
      "['bond', 'learn', 'be-entertained']": 1,
      "['play', 'be-entertained', 'bond']": 1,
      "['learn', 'explore', 'bond']": 1,
      "['celebrate', 'be-entertained', 'learn']": 1,
      "['celebrate', 'learn', 'explore']": 1,
      "['bond', 'play', 'explore']": 2,
      "['celebrate', 'play', 'bond']": 1,
      "['be-entertained', 'learn', 'be-inspired']": 1,
      "['explore', 'be-inspired', 'relax']": 1,
      "['be-entertained', 'learn', 'bond']": 1,
      "['learn', 'play', 'explore']": 2,
      "['play', 'create', 'bond']": 1,
      "['learn', 'improve-health']": 1,
      "['learn', 'improve-health', 'play']": 1,
      "['play', 'bond', 'support-community']": 1,
      "['support-community', 'bond', 'learn']": 1,
      "['play', 'learn', 'bond']": 3,
      "['learn', 'support-community', 'socialize']": 1,
      "['support-community', 'learn', 'bond']": 2,
      "['create', 'learn', 'bond']": 1,
      "['bond', 'learn', 'socialize']": 1,
      "['learn', 'support-community']": 1,
      "['bond', 'play', 'dance-party']": 1,
      "['bond', 'play', 'be-inspired']": 2,
      "['be-entertained', 'socialize']": 2,
      "['support-community', 'socialize', 'celebrate']": 2,
      "['celebrate', 'bond', 'socialize']": 1,
      "['learn', 'bond', 'improve-health']": 1,
      "['be-entertained', 'dance-party', 'bond']": 1,
      "['relax', 'socialize', 'bond']": 1,
      "['celebrate', 'bond', 'be-entertained']": 1,
      "['be-entertained', 'learn', 'socialize']": 1,
      "['dance-party', 'socialize', 'celebrate']": 1,
      "['create', 'be-inspired', 'socialize']": 1,
      "['bond', 'play', 'socialize']": 2,
      "['bond', 'create', 'learn']": 1,
      "['explore', 'bond', 'play']": 1,
      "['socialize', 'learn', 'bond']": 1,
      "['discover-tech', 'learn', 'socialize']": 1,
      "['be-entertained', 'socialize', 'relax']": 2,
      "['learn', 'discover-tech', 'socialize']": 1,
      "['support-community', 'bond', 'relax']": 1,
      "['learn', 'create', 'be-inspired']": 1,
      "['bond', 'explore', 'learn']": 1,
      "['be-entertained', 'bond', 'relax']": 1,
      "['be-entertained', 'socialize', 'learn']": 2,
      "['learn', 'explore', 'relax']": 1,
      "['create', 'socialize', 'bond']": 1,
      "['celebrate', 'bond', 'play']": 2,
      "['learn', 'support-community', 'bond']": 1,
      "['be-inspired', 'learn']": 1,
      "['support-community', 'bond', 'play']": 3,
      "['learn', 'socialize', 'explore']": 1,
      "['improve-health', 'socialize', 'support-community']": 1,
      "['improve-health', 'explore', 'celebrate']": 1,
      "['compete', 'improve-health', 'explore']": 1,
      "['support-community', 'explore', 'socialize']": 1,
      "['bond', 'play', 'relax']": 1,
      "['improve-health', 'support-community', 'compete']": 2,
      "['improve-health', 'compete', 'support-community']": 1,
      "['improve-health', 'bond', 'play']": 1,
      "['be-entertained', 'be-inspired', 'bond']": 1,
      "['improve-health', 'support-community']": 1,
      "['play', 'improve-health', 'support-community']": 1,
      "['improve-health', 'support-community', 'bond']": 2,
      "['improve-health', 'play', 'bond']": 1,
      "['be-entertained', 'play']": 1,
      "['bond', 'be-entertained', 'be-inspired']": 1,
      "['celebrate', 'bond', 'create']": 1,
      "['celebrate', 'bond', 'relax']": 1,
      "['be-inspired', 'learn', 'explore']": 1,
      "['learn', 'be-inspired', 'bond']": 1,
      "['learn', 'explore']": 1
    },
    "by_is_free": {
      "free": 120,
      "paid": 84
    },
    "by_age_bucket_best_from": {
      "6-8": 28,
      "3-5": 90,
      "9-12": 8,
      "0-2": 66,
      "13+": 12
    },
    "by_price_band": {
      "free": 120,
      "1_10": 9,
      "11_20": 15,
      "21_50": 42,
      "51_plus": 18
    }
  },
  "interest_upper_bounds": {
    "arts": 36,
    "science": 11,
    "music": 46,
    "outdoors": 11,
    "theater": 19,
    "books": 14,
    "sports": 17,
    "food": 16,
    "film": 2
  }
}